{
  "timestamp": "2026-07-17T22:51:37.733Z",
  "gameDetails": {
    "id": "37628",
    "name": "Haggis",
    "type": "boardgame",
    "description": "Haggis is a climbing game in the same family as Zheng Fen and Big Two. It borrows and recombines elements from its parent games - card combinations, bombs, scoring for cards in hand, scoring for cards collected in tricks - and it mixes in equally distributed wild cards and betting that you'll be the first to empty your hand of cards.\n\n",
    "image": "https://cf.geekdo-images.com/IrYxdDL_emPurvpg_lRSgA__original/img/HfyjZXoZEDvDU9Hu7EiFbEWlcm4=/0x0/filters:format(jpeg)/pic7669050.jpg",
    "thumbnail": "https://cf.geekdo-images.com/IrYxdDL_emPurvpg_lRSgA__small/img/BRBs8AvHhWUQzb2MWcwglmJaiBM=/fit-in/200x150/filters:strip_icc()/pic7669050.jpg",
    "link": "https://boardgamegeek.com/thing/37628",
    "minPlayers": "2",
    "maxPlayers": "4",
    "yearPublished": "2010",
    "playingTime": "45",
    "minPlayingTime": "45",
    "maxPlayingTime": "45",
    "bestAtCount": [
      2
    ],
    "averageRating": "7.03044",
    "averageWeight": "2.0996",
    "boardGameRank": "1231",
    "mechanics": [
      "Betting and Bluffing",
      "Hand Management",
      "Ladder Climbing",
      "Team-Based Game"
    ],
    "categories": [
      "Card Game"
    ],
    "designers": [
      "Sean Ross (I)"
    ],
    "videoLink": "https://www.youtube.com/watch?v=9Z43bS9kuh8"
  }
}